starlette_babel/__init__.py
starlette_babel/contrib/__init__.py
starlette_babel/contrib/jinja.py
starlette_babel/formatters.py
starlette_babel/locale.py
starlette_babel/py.typed
starlette_babel/timezone.py
starlette_babel/translator.py
starlette_babel-1.0.3.dist-info/LICENSE
starlette_babel-1.0.3.dist-info/METADATA
starlette_babel-1.0.3.dist-info/WHEEL
starlette_babel-1.0.3.dist-info/RECORD
