Metadata-Version: 2.1
Name: starlette_babel
Version: 1.0.3
Summary: Locale support for Starlette
Home-page: https://github.com/alex-oleshkevich/starlette_babel
License: MIT
Author: Alex Oleshkevich
Author-email: alex.oleshkevich@gmail.com
Requires-Python: >=3.10,<4.0
Classifier: Development Status :: 5 - Production/Stable
Classifier: Environment :: Web Environment
Classifier: Intended Audience :: Developers
Classifier: License :: OSI Approved :: MIT License
Classifier: Operating System :: OS Independent
Classifier: Programming Language :: Python :: 3
Classifier: Programming Language :: Python :: 3.10
Classifier: Programming Language :: Python :: 3.11
Classifier: Programming Language :: Python :: 3.12
Classifier: Programming Language :: Python :: 3.13
Classifier: Topic :: Software Development :: Libraries :: Python Modules
Classifier: Typing :: Typed
Requires-Dist: Babel (>=2.12,<3.0)
Requires-Dist: pytz
Requires-Dist: starlette
Project-URL: Documentation, https://github.com/alex-oleshkevich/starlette_babel
Project-URL: Repository, https://github.com/alex-oleshkevich/starlette_babel
